pyilcd/__init__.py
pyilcd/common.py
pyilcd/config.py
pyilcd/contact_dataset.py
pyilcd/core.py
pyilcd/flow_dataset.py
pyilcd/flow_property_dataset.py
pyilcd/helpers.py
pyilcd/process_dataset.py
pyilcd/source_dataset.py
pyilcd/unit_group_dataset.py
pyilcd/schemas/ILCD_Categories.xsd
pyilcd/schemas/ILCD_Common_DataTypes.xsd
pyilcd/schemas/ILCD_Common_EnumerationValues.xsd
pyilcd/schemas/ILCD_Common_Groups.xsd
pyilcd/schemas/ILCD_Common_Validation.xsd
pyilcd/schemas/ILCD_ContactDataSet.xsd
pyilcd/schemas/ILCD_Documentation.xsd
pyilcd/schemas/ILCD_FlowDataSet.xsd
pyilcd/schemas/ILCD_FlowPropertyDataSet.xsd
pyilcd/schemas/ILCD_ILCD.xsd
pyilcd/schemas/ILCD_LCIAMethodDataSet.xsd
pyilcd/schemas/ILCD_LCIAMethodologies.xsd
pyilcd/schemas/ILCD_Locations.xsd
pyilcd/schemas/ILCD_ProcessDataSet.xsd
pyilcd/schemas/ILCD_SourceDataSet.xsd
pyilcd/schemas/ILCD_UnitGroupDataSet.xsd
pyilcd-6.3.1.dist-info/LICENSE
pyilcd-6.3.1.dist-info/METADATA
pyilcd-6.3.1.dist-info/WHEEL
pyilcd-6.3.1.dist-info/top_level.txt
pyilcd-6.3.1.dist-info/RECORD
