Metadata-Version: 2.1
Name: pyilcd
Version: 6.3.1
Summary: A Python package that converts ILCD XML formats to their Python equivalents and export the same data back to XML.
Author-email: Mina Sami <sami.mg@outlook.com>
Maintainer-email: Mina Sami <sami.mg@outlook.com>
Project-URL: source, https://github.com/sami-m-g/pyilcd
Project-URL: homepage, https://github.com/sami-m-g/pyilcd
Project-URL: tracker, https://github.com/sami-m-g/pyilcd/issues
Classifier: Development Status :: 4 - Beta
Classifier: Programming Language :: Python
Classifier: Programming Language :: Python :: 3
Classifier: Programming Language :: Python :: 3.8
Classifier: Programming Language :: Python :: 3.9
Classifier: Programming Language :: Python :: 3.10
Classifier: Programming Language :: Python :: 3.11
Classifier: Programming Language :: Python :: 3.12
Classifier: Natural Language :: English
Classifier: Operating System :: OS Independent
Requires-Python: >=3.8
License-File: LICENSE
Requires-Dist: lxml ==4.9.2
Requires-Dist: lxmlh >=1.2.0
Requires-Dist: pycasreg ==0.1.0
Provides-Extra: dev
Requires-Dist: build ; extra == 'dev'
Requires-Dist: pre-commit ; extra == 'dev'
Requires-Dist: pylint ; extra == 'dev'
Requires-Dist: pytest ; extra == 'dev'
Requires-Dist: pytest-cov ; extra == 'dev'
Requires-Dist: pytest-randomly ; extra == 'dev'
Requires-Dist: setuptools ; extra == 'dev'
Requires-Dist: sphinx ; extra == 'dev'
Requires-Dist: sphinx-rtd-theme ; extra == 'dev'
Provides-Extra: testing
Requires-Dist: pyilcd ; extra == 'testing'
Requires-Dist: pytest ; extra == 'testing'
Requires-Dist: pytest-cov ; extra == 'testing'
Requires-Dist: python-coveralls ; extra == 'testing'
